servermine/__init__.py
servermine/client.py
servermine/client_redis.py
servermine/lib/__init__.py
servermine/lib/acl.py
servermine/lib/redis_lib.py
servermine-1.0.23.dist-info/METADATA
servermine-1.0.23.dist-info/WHEEL
servermine-1.0.23.dist-info/top_level.txt
servermine-1.0.23.dist-info/RECORD
