Metadata-Version: 2.1
Name: servermine
Version: 1.0.23
Summary: Python library to connect to ServerMine services
Home-page: https://www.servermine.io
Author: Thiago Magro
Author-email: thiago.magro@gmail.com
Classifier: Programming Language :: Python :: 3
Classifier: License :: OSI Approved :: MIT License
Classifier: Operating System :: OS Independent
Requires-Python: >=3.6
Requires-Dist: redis
